pimple.py
pimple-0.2.3.dist-info/LICENSE
pimple-0.2.3.dist-info/METADATA
pimple-0.2.3.dist-info/WHEEL
pimple-0.2.3.dist-info/entry_points.txt
pimple-0.2.3.dist-info/top_level.txt
pimple-0.2.3.dist-info/RECORD
