Metadata-Version: 2.1
Name: pimple
Version: 0.2.3
Summary: Summarize your unit tests
Home-page: https://github.com/samueljsb/pimple
Author: Samuel Searles-Bryant
Author-email: devel@samueljsb.co.uk
License: UNKNOWN
Platform: UNKNOWN
Classifier: Development Status :: 3 - Alpha
Classifier: Intended Audience :: Developers
Classifier: Programming Language :: Python :: 3.6
Classifier: Programming Language :: Python :: 3.7
Classifier: License :: OSI Approved :: MIT License
Classifier: Topic :: Software Development :: Documentation
Classifier: Topic :: Software Development :: Testing
Classifier: Topic :: Utilities
Requires-Dist: click
